MANIFEST.in
README.rst
setup.py
bin/filterfiles.py
bin/pypore_batch_csv.py
src/pypore/__init__.py
src/pypore/data_file_opener.c
src/pypore/event_finder.c
src/pypore/file_converter.py
src/pypore/filter_files.py
src/pypore/version.py
src/pypore.egg-info/PKG-INFO
src/pypore.egg-info/SOURCES.txt
src/pypore.egg-info/dependency_links.txt
src/pypore.egg-info/top_level.txt
src/pypore/filetypes/__init__.py
src/pypore/filetypes/data_file.py
src/pypore/filetypes/event_database.py
src/pypore/filetypes/tests/__init__.py
src/pypore/filetypes/tests/test_event_database.py
src/pypore/i_o/__init__.py
src/pypore/i_o/abstract_reader.c
src/pypore/i_o/chimera_reader.c
src/pypore/i_o/cnp2_reader.c
src/pypore/i_o/data_file_reader.c
src/pypore/i_o/heka_reader.c
src/pypore/i_o/workerobjects.py
src/pypore/i_o/tests/__init__.py
src/pypore/i_o/tests/reader_tests.py
src/pypore/i_o/tests/test_chimera_reader.py
src/pypore/i_o/tests/test_cnp2_reader.py
src/pypore/i_o/tests/test_datafile_reader.py
src/pypore/i_o/tests/test_heka_reader.py
src/pypore/sampledata/__init__.py
src/pypore/sampledata/creator.py
src/pypore/sampledata/testing_files.py
src/pypore/sampledata/testDataFiles/chimera_1event.h5
src/pypore/sampledata/testDataFiles/chimera_1event.log
src/pypore/sampledata/testDataFiles/chimera_1event.mat
src/pypore/sampledata/testDataFiles/chimera_1event_2levels.h5
src/pypore/sampledata/testDataFiles/chimera_1event_2levels.log
src/pypore/sampledata/testDataFiles/chimera_1event_2levels.mat
src/pypore/sampledata/testDataFiles/chimera_empty.log
src/pypore/sampledata/testDataFiles/chimera_nonoise_1event.h5
src/pypore/sampledata/testDataFiles/chimera_nonoise_1event.log
src/pypore/sampledata/testDataFiles/chimera_nonoise_1event.mat
src/pypore/sampledata/testDataFiles/chimera_nonoise_1event_2levels.h5
src/pypore/sampledata/testDataFiles/chimera_nonoise_1event_2levels.log
src/pypore/sampledata/testDataFiles/chimera_nonoise_1event_2levels.mat
src/pypore/sampledata/testDataFiles/chimera_nonoise_2events_1levels.log
src/pypore/sampledata/testDataFiles/chimera_nonoise_2events_1levels.mat
src/pypore/sampledata/testDataFiles/chimera_small.h5
