Metadata-Version: 1.1
Name: pypore
Version: 0.0.6.dev20180322185748
Summary: Pythonic/Cythonic Nanopore Translocation Analysis
Home-page: http://parkin.github.io/pypore/
Author: Will Parkin
Author-email: wmparkin@gmail.com
License: UNKNOWN
Platform: UNKNOWN
Requires: numpy
Requires: scipy
Requires: tables
Requires: PySide
Requires: pyqtgraph
